smart_tfrecord_writer/__init__.py
smart_tfrecord_writer/tfrecord_protos.py
smart_tfrecord_writer/utils.py
smart_tfrecord_writer/writer.py
smart_tfrecord_writer-0.1.0.dist-info/LICENSE
smart_tfrecord_writer-0.1.0.dist-info/METADATA
smart_tfrecord_writer-0.1.0.dist-info/WHEEL
smart_tfrecord_writer-0.1.0.dist-info/RECORD
