Metadata-Version: 2.1
Name: smart-tfrecord-writer
Version: 0.1.0
Summary: A Python package to write TFRecord files easily and seamlessly into Tensorflow Datasets format.
Home-page: https://github.com/caharper/smart-tfrecord-writer
License: Apache-2.0
Keywords: tfrecord,dataset,machine learning
Author: caharper
Author-email: caharper@smu.edu
Requires-Python: >=3.10,<3.12
Classifier: Intended Audience :: Science/Research
Classifier: License :: OSI Approved :: Apache Software License
Classifier: Programming Language :: Python :: 3
Classifier: Programming Language :: Python :: 3.10
Classifier: Programming Language :: Python :: 3.11
Classifier: Topic :: Scientific/Engineering
Classifier: Topic :: Scientific/Engineering :: Artificial Intelligence
Requires-Dist: scikit-learn (>=1.4.0,<2.0.0)
Requires-Dist: tensorflow (>=2.0)
Requires-Dist: tensorflow-datasets (>=4.9.4,<5.0.0)
Requires-Dist: termcolor (>=2.4.0,<3.0.0)
Requires-Dist: tqdm (>=4.66.1,<5.0.0)
Project-URL: Repository, https://github.com/caharper/smart-tfrecord-writer
